holado/__init__.py
holado/holado_config.py
holado/common/__init__.py
holado/common/context/__init__.py
holado/common/context/context.py
holado/common/context/service_manager.py
holado/common/context/session_context.py
holado/common/handlers/__init__.py
holado/common/handlers/enums.py
holado/common/handlers/object.py
holado/common/handlers/undefined.py
holado/common/tools/__init__.py
holado/common/tools/gc_manager.py
holado_ais/__init__.py
holado_ais/ais/MaritimeIdentificationDigits.csv
holado_ais/ais/ais_manager.py
holado_ais/ais/ais_messages.py
holado_ais/ais/ais_payload.py
holado_ais/ais/enums.py
holado_ais/ais/patch_pyais.py
holado_ais/tests/behave/steps/__init__.py
holado_ais/tests/behave/steps/ais/__init__.py
holado_ais/tests/behave/steps/ais/ais_manager_steps.py
holado_ais/tests/behave/steps/ais/ais_messages_steps.py
holado_binary/__init__.py
holado_binary/ipc/binary.py
holado_binary/ipc/bit_series.py
holado_binary/tests/behave/steps/__init__.py
holado_binary/tests/behave/steps/ipc/binary_steps.py
holado_binary/tests/behave/steps/ipc/bit_series_steps.py
holado_context/__init__.py
holado_context/tests/behave/steps/__init__.py
holado_context/tests/behave/steps/private/__init__.py
holado_context/tests/behave/steps/private/common/context_steps.py
holado_core/__init__.py
holado_core/common/__init__.py
holado_core/common/actors/actions.py
holado_core/common/actors/actor.py
holado_core/common/actors/element_actor.py
holado_core/common/actors/find_actor.py
holado_core/common/actors/tree_actor.py
holado_core/common/actors/verify_actions.py
holado_core/common/block/base.py
holado_core/common/block/block_manager.py
holado_core/common/block/block_method.py
holado_core/common/block/block_steps.py
holado_core/common/block/function.py
holado_core/common/block/scope_function.py
holado_core/common/block/scope_manager.py
holado_core/common/block/scope_steps.py
holado_core/common/criterias/and_criteria.py
holado_core/common/criterias/criteria.py
holado-0.16.5.dist-info/METADATA
holado-0.16.5.dist-info/WHEEL
holado-0.16.5.dist-info/licenses/LICENSE
holado-0.16.5.dist-info/RECORD
