Metadata-Version: 2.4
Name: holado
Version: 0.16.5
Summary: HolAdo framework
Project-URL: Homepage, https://gitlab.com/holado_framework/python
Project-URL: Issues, https://gitlab.com/holado_framework/python/-/issues
Author-email: Eric Klumpp <eric.klumpp@gmail.com>
License-Expression: MIT
License-File: LICENSE
Keywords: AIS,BDD,Behavior Driver Development,Behaviour Driven Development,DB,JSON,Keycloak,Protobuf,REST,RabbitMQ,Redis,S3,Specification By Example,Web Services,XML,YAML,automation,docker,email,functional test,gRPC,logging,multitask,script,test,test automation
Classifier: Development Status :: 5 - Production/Stable
Classifier: Operating System :: OS Independent
Classifier: Programming Language :: Python :: 3
Classifier: Programming Language :: Python :: 3.10
Classifier: Programming Language :: Python :: 3.11
Classifier: Programming Language :: Python :: 3.12
Requires-Python: >=3.10
Requires-Dist: behave
Requires-Dist: duration-parser
Requires-Dist: lxml
Requires-Dist: psutil
Requires-Dist: pypika
Requires-Dist: python-dateutil
Requires-Dist: sql-metadata
Requires-Dist: xmltodict
Provides-Extra: ais
Requires-Dist: pyais; extra == 'ais'
Provides-Extra: all
Requires-Dist: boto3; extra == 'all'
Requires-Dist: certifi; extra == 'all'
Requires-Dist: connexion[flask,swagger-ui,uvicorn]; extra == 'all'
Requires-Dist: cryptography; extra == 'all'
Requires-Dist: docker; extra == 'all'
Requires-Dist: flask; extra == 'all'
Requires-Dist: flask-cors; extra == 'all'
Requires-Dist: google; extra == 'all'
Requires-Dist: google-api-core; extra == 'all'
Requires-Dist: grpc-requests; extra == 'all'
Requires-Dist: grpcio; extra == 'all'
Requires-Dist: grpcio-reflection; extra == 'all'
Requires-Dist: grpcio-tools; extra == 'all'
Requires-Dist: minio; extra == 'all'
Requires-Dist: moto; extra == 'all'
Requires-Dist: paramiko<4.0.0; extra == 'all'
Requires-Dist: pika; extra == 'all'
Requires-Dist: prettytable; extra == 'all'
Requires-Dist: protobuf; extra == 'all'
Requires-Dist: psycopg; extra == 'all'
Requires-Dist: psycopg-binary; extra == 'all'
Requires-Dist: pyais; extra == 'all'
Requires-Dist: pympler; extra == 'all'
Requires-Dist: pysftp; extra == 'all'
Requires-Dist: redis; extra == 'all'
Requires-Dist: redis-om; extra == 'all'
Requires-Dist: ruamel-yaml; extra == 'all'
Requires-Dist: sftpserver; extra == 'all'
Requires-Dist: truststore; extra == 'all'
Requires-Dist: zeep; extra == 'all'
Provides-Extra: api-connexion
Requires-Dist: connexion[flask,swagger-ui,uvicorn]; extra == 'api-connexion'
Provides-Extra: db-postgresql
Requires-Dist: psycopg; extra == 'db-postgresql'
Requires-Dist: psycopg-binary; extra == 'db-postgresql'
Provides-Extra: docker
Requires-Dist: docker; extra == 'docker'
Requires-Dist: prettytable; extra == 'docker'
Provides-Extra: grpc
Requires-Dist: google; extra == 'grpc'
Requires-Dist: google-api-core; extra == 'grpc'
Requires-Dist: grpc-requests; extra == 'grpc'
Requires-Dist: grpcio; extra == 'grpc'
Requires-Dist: grpcio-reflection; extra == 'grpc'
Requires-Dist: grpcio-tools; extra == 'grpc'
Requires-Dist: protobuf; extra == 'grpc'
Provides-Extra: helper-debug
Requires-Dist: pympler; extra == 'helper-debug'
Provides-Extra: protobuf
Requires-Dist: google; extra == 'protobuf'
Requires-Dist: google-api-core; extra == 'protobuf'
Requires-Dist: protobuf; extra == 'protobuf'
Provides-Extra: rabbitmq
Requires-Dist: pika; extra == 'rabbitmq'
Provides-Extra: redis
Requires-Dist: redis; extra == 'redis'
Requires-Dist: redis-om; extra == 'redis'
Provides-Extra: s3
Requires-Dist: boto3; extra == 's3'
Requires-Dist: flask; extra == 's3'
Requires-Dist: flask-cors; extra == 's3'
Requires-Dist: minio; extra == 's3'
Requires-Dist: moto; extra == 's3'
Provides-Extra: sftp
Requires-Dist: certifi; extra == 'sftp'
Requires-Dist: cryptography; extra == 'sftp'
Requires-Dist: paramiko<4.0.0; extra == 'sftp'
Requires-Dist: pysftp; extra == 'sftp'
Requires-Dist: sftpserver; extra == 'sftp'
Requires-Dist: truststore; extra == 'sftp'
Provides-Extra: ssl
Requires-Dist: certifi; extra == 'ssl'
Requires-Dist: cryptography; extra == 'ssl'
Requires-Dist: truststore; extra == 'ssl'
Provides-Extra: ws-suds
Requires-Dist: suds; extra == 'ws-suds'
Provides-Extra: ws-zeep
Requires-Dist: zeep; extra == 'ws-zeep'
Provides-Extra: yaml
Requires-Dist: ruamel-yaml; extra == 'yaml'
